{
  "rootId": "11",
  "description": [
    "More eco-friendly and less straining, avocado vibe cells, with a core of fluid ivory.",
    "The sample has some eerieness to it, however."
  ],
  "attributes": {
    "toxicity": 0.1,
    "swarm": 0.7
  },
  "nodes": {
    "11": {
      "type": "root",
      "x": 1201.3224791283706,
      "y": 135.62564565615898,
      "width": 200,
      "height": 212,
      "layer": 10,
      "fields": {
        "point": {
          "kind": "static",
          "type": "vec3",
          "value": {
            "x": 0,
            "y": 0,
            "z": 0
          },
          "internal": true,
          "anchor": {
            "size": 16,
            "x": 0,
            "y": -4,
            "type": "field",
            "active": false,
            "hovered": false
          }
        },
        "color": {
          "kind": "dynamic",
          "type": "vec3",
          "value": {
            "nodeId": "12"
          },
          "inputLocked": true,
          "anchor": {
            "size": 16,
            "x": 0,
            "y": 45.035714285714285,
            "type": "field",
            "active": false,
            "hovered": false
          },
          "previousStaticValue": {
            "x": 0,
            "y": 0,
            "z": 0
          }
        },
        "dithering": {
          "kind": "dynamic",
          "type": "float",
          "value": 0,
          "anchor": {
            "size": 16,
            "x": 0,
            "y": 75.32142857142857,
            "type": "field",
            "active": false,
            "hovered": false
          }
        },
        "scale": {
          "kind": "static",
          "type": "float",
          "value": 0.0080092,
          "min": 0.00001,
          "max": 0.1,
          "excludeFromFunction": true,
          "anchor": {
            "size": 16,
            "x": 0,
            "y": 105.60714285714286,
            "type": "field",
            "active": false,
            "hovered": false
          }
        },
        "speedX": {
          "kind": "static",
          "type": "float",
          "value": 0,
          "min": -1,
          "max": 1,
          "excludeFromFunction": true,
          "anchor": {
            "size": 16,
            "x": 0,
            "y": 135.89285714285714,
            "type": "field",
            "active": false,
            "hovered": false
          }
        },
        "speedY": {
          "kind": "static",
          "type": "float",
          "value": 0,
          "min": -1,
          "max": 1,
          "excludeFromFunction": true,
          "anchor": {
            "size": 16,
            "x": 0,
            "y": 166.17857142857142,
            "type": "field",
            "active": false,
            "hovered": false
          }
        },
        "speedZ": {
          "kind": "static",
          "type": "float",
          "value": 0.1,
          "min": -1,
          "max": 1,
          "excludeFromFunction": true,
          "anchor": {
            "size": 16,
            "x": 0,
            "y": 196.46428571428572,
            "type": "field",
            "active": false,
            "hovered": false
          }
        },
        "ditheringTextureDimensions": {
          "kind": "static",
          "type": "vec2",
          "value": {
            "x": 128,
            "y": 128
          },
          "hidden": true,
          "anchor": {
            "size": 16,
            "x": 0,
            "y": -4,
            "type": "field",
            "active": false,
            "hovered": false
          }
        },
        "tDithering": {
          "kind": "static",
          "type": "sampler2D",
          "value": {
            "metadata": {
              "version": 4.5,
              "type": "Texture",
              "generator": "Texture.toJSON"
            },
            "uuid": "5ec9b64e-8105-4f19-8e74-9a50ea1c483c",
            "name": "",
            "image": "5ee7a0c3-80f4-4fbf-8c63-809a73ccbc1c",
            "mapping": 300,
            "repeat": [
              1,
              1
            ],
            "offset": [
              0,
              0
            ],
            "center": [
              0,
              0
            ],
            "rotation": 0,
            "wrap": [
              1000,
              1000
            ],
            "format": 1023,
            "type": 1009,
            "encoding": 3000,
            "minFilter": 1003,
            "magFilter": 1003,
            "anisotropy": 1,
            "flipY": true,
            "premultiplyAlpha": false,
            "unpackAlignment": 4
          },
          "hidden": true,
          "anchor": {
            "size": 16,
            "x": 0,
            "y": -4,
            "type": "field",
            "active": false,
            "hovered": false
          }
        }
      },
      "returnType": "vec3",
      "id": "11",
      "hovered": false,
      "active": false,
      "elevated": false
    },
    "12": {
      "type": "hsvToRgb",
      "x": 934.5071734062051,
      "y": 113.80258365225916,
      "width": 200,
      "height": 134,
      "anchor": {
        "size": 16,
        "x": 200,
        "y": 67,
        "type": "node",
        "hovered": false,
        "active": false
      },
      "layer": 13,
      "fields": {
        "hue": {
          "kind": "dynamic",
          "type": "float",
          "value": {
            "nodeId": "29"
          },
          "anchor": {
            "size": 16,
            "x": 0,
            "y": 48.25,
            "type": "field",
            "hovered": false,
            "active": false
          },
          "previousStaticValue": 0
        },
        "saturation": {
          "kind": "dynamic",
          "type": "float",
          "value": {
            "nodeId": "31"
          },
          "anchor": {
            "size": 16,
            "x": 0,
            "y": 81.75,
            "type": "field",
            "hovered": false,
            "active": false
          },
          "previousStaticValue": 0
        },
        "value": {
          "kind": "dynamic",
          "type": "float",
          "value": {
            "nodeId": "24"
          },
          "anchor": {
            "size": 16,
            "x": 0,
            "y": 115.25,
            "type": "field",
            "hovered": false,
            "active": false
          },
          "previousStaticValue": 0.5
        }
      },
      "returnType": "vec3",
      "id": "12",
      "hovered": false,
      "active": false,
      "elevated": false
    },
    "15": {
      "type": "circle",
      "x": 77.02864084235546,
      "y": 26.336670485028463,
      "width": 200,
      "height": 238,
      "anchor": {
        "size": 16,
        "x": 200,
        "y": 119,
        "type": "node",
        "hovered": false,
        "active": false
      },
      "layer": 28,
      "fields": {
        "point": {
          "kind": "dynamic",
          "type": "vec3",
          "value": {
            "nodeId": "16"
          },
          "internalOptional": true,
          "anchor": {
            "size": 16,
            "x": 0,
            "y": 44.5,
            "type": "field",
            "hovered": false,
            "active": false
          },
          "previousStaticValue": {
            "x": 0,
            "y": 0,
            "z": 0
          }
        },
        "scale": {
          "kind": "static",
          "type": "float",
          "internal": true,
          "anchor": {
            "size": 16,
            "x": 0,
            "y": -4,
            "type": "field",
            "active": false,
            "hovered": false
          }
        },
        "radius": {
          "kind": "dynamic",
          "type": "float",
          "value": {
            "nodeId": "20"
          },
          "min": 0,
          "max": 1000,
          "anchor": {
            "size": 16,
            "x": 0,
            "y": 74.25,
            "type": "field",
            "hovered": false,
            "active": false
          },
          "previousStaticValue": 460
        },
        "x": {
          "kind": "dynamic",
          "type": "float",
          "value": 0,
          "min": -1000,
          "max": 1000,
          "anchor": {
            "size": 16,
            "x": 0,
            "y": 104,
            "type": "field",
            "hovered": false,
            "active": false
          }
        },
        "y": {
          "kind": "dynamic",
          "type": "float",
          "value": 0,
          "min": -1000,
          "max": 1000,
          "anchor": {
            "size": 16,
            "x": 0,
            "y": 133.75,
            "type": "field",
            "hovered": false,
            "active": false
          }
        },
        "outsideBrightness": {
          "kind": "dynamic",
          "type": "float",
          "value": 1,
          "min": 0,
          "max": 1,
          "anchor": {
            "size": 16,
            "x": 0,
            "y": 163.5,
            "type": "field",
            "hovered": false,
            "active": false
          }
        },
        "insideBrightness": {
          "kind": "dynamic",
          "type": "float",
          "value": 0,
          "min": 0,
          "max": 1,
          "anchor": {
            "size": 16,
            "x": 0,
            "y": 193.25,
            "type": "field",
            "hovered": false,
            "active": false
          }
        },
        "softness": {
          "kind": "dynamic",
          "type": "float",
          "value": 0.96,
          "min": 0,
          "max": 1,
          "anchor": {
            "size": 16,
            "x": 0,
            "y": 223,
            "type": "field",
            "hovered": false,
            "active": false
          }
        }
      },
      "returnType": "float",
      "id": "15",
      "elevated": false,
      "active": false,
      "hovered": false
    },
    "16": {
      "type": "polarDisplace",
      "x": -370.0906560636182,
      "y": -124.16013916501,
      "width": 200,
      "height": 160,
      "anchor": {
        "size": 16,
        "x": 200,
        "y": 80,
        "type": "node",
        "hovered": false,
        "active": false
      },
      "layer": 16,
      "fields": {
        "point": {
          "kind": "dynamic",
          "type": "vec3",
          "value": {
            "x": 0,
            "y": 0,
            "z": 0
          },
          "internalOptional": true,
          "anchor": {
            "size": 16,
            "x": 0,
            "y": 46.75,
            "type": "field",
            "hovered": false,
            "active": false
          },
          "previousStaticValue": {
            "x": 0,
            "y": 0,
            "z": 0
          }
        },
        "angle1": {
          "kind": "dynamic",
          "type": "float",
          "value": {
            "nodeId": "28"
          },
          "min": -3.141592653589793,
          "max": 3.141592653589793,
          "anchor": {
            "size": 16,
            "x": 0,
            "y": 78.75,
            "type": "field",
            "hovered": false,
            "active": false
          },
          "previousStaticValue": 0.628318530717959
        },
        "angle2": {
          "kind": "dynamic",
          "type": "float",
          "value": 1.94778744522567,
          "min": -3.141592653589793,
          "max": 3.141592653589793,
          "anchor": {
            "size": 16,
            "x": 0,
            "y": 110.75,
            "type": "field",
            "hovered": false,
            "active": false
          }
        },
        "radius": {
          "kind": "dynamic",
          "type": "float",
          "value": {
            "nodeId": "17"
          },
          "min": -5,
          "max": 5,
          "anchor": {
            "size": 16,
            "x": 0,
            "y": 142.75,
            "type": "field",
            "hovered": false,
            "active": false
          },
          "previousStaticValue": 0.4
        }
      },
      "returnType": "vec3",
      "id": "16",
      "elevated": false,
      "active": false,
      "hovered": false
    },
    "17": {
      "type": "simplex",
      "x": -1009.859443433381,
      "y": -62.90724758630506,
      "width": 200,
      "height": 290,
      "anchor": {
        "size": 16,
        "x": 200,
        "y": 145,
        "type": "node",
        "hovered": false,
        "active": false
      },
      "layer": 15,
      "fields": {
        "point": {
          "kind": "dynamic",
          "type": "vec3",
          "value": {
            "x": 0,
            "y": 0,
            "z": 0
          },
          "internalOptional": true,
          "anchor": {
            "size": 16,
            "x": 0,
            "y": 43.75,
            "type": "field",
            "hovered": false,
            "active": false
          }
        },
        "frequency": {
          "kind": "dynamic",
          "type": "float",
          "value": 0.8,
          "min": 0,
          "max": 10,
          "anchor": {
            "size": 16,
            "x": 0,
            "y": 72.75,
            "type": "field",
            "active": false,
            "hovered": false
          }
        },
        "amplitude": {
          "kind": "dynamic",
          "type": "float",
          "value": 1,
          "min": 0,
          "max": 10,
          "anchor": {
            "size": 16,
            "x": 0,
            "y": 101.75,
            "type": "field",
            "hovered": false,
            "active": false
          }
        },
        "persistance": {
          "kind": "dynamic",
          "type": "float",
          "value": 0.5,
          "min": 0,
          "max": 1,
          "anchor": {
            "size": 16,
            "x": 0,
            "y": 130.75,
            "type": "field",
            "active": false,
            "hovered": false
          }
        },
        "lacunarity": {
          "kind": "dynamic",
          "type": "float",
          "value": 0.7,
          "min": 0,
          "max": 10,
          "anchor": {
            "size": 16,
            "x": 0,
            "y": 159.75,
            "type": "field",
            "active": false,
            "hovered": false
          }
        },
        "octaves": {
          "kind": "static",
          "type": "int",
          "value": 3,
          "min": 1,
          "max": 5,
          "restricted": true,
          "anchor": {
            "size": 16,
            "x": 0,
            "y": 188.75,
            "type": "field",
            "active": false,
            "hovered": false
          }
        },
        "exponent": {
          "kind": "dynamic",
          "type": "float",
          "value": 1,
          "min": 0.01,
          "max": 10,
          "anchor": {
            "size": 16,
            "x": 0,
            "y": 217.75,
            "type": "field",
            "hovered": false,
            "active": false
          }
        },
        "ridge": {
          "kind": "dynamic",
          "type": "float",
          "value": 0.4006,
          "min": 0.001,
          "max": 1,
          "restricted": true,
          "anchor": {
            "size": 16,
            "x": 0,
            "y": 246.75,
            "type": "field",
            "hovered": false,
            "active": false
          }
        },
        "normalize": {
          "kind": "static",
          "type": "bool",
          "value": true,
          "anchor": {
            "size": 16,
            "x": 0,
            "y": 275.75,
            "type": "field",
            "active": false,
            "hovered": false
          }
        }
      },
      "returnType": "float",
      "id": "17",
      "elevated": false,
      "active": false,
      "hovered": false
    },
    "19": {
      "type": "simplex",
      "x": -675.6111332007958,
      "y": 158.13071570576534,
      "width": 200,
      "height": 290,
      "anchor": {
        "size": 16,
        "x": 200,
        "y": 145,
        "type": "node",
        "hovered": false,
        "active": false
      },
      "layer": 19,
      "fields": {
        "point": {
          "kind": "dynamic",
          "type": "vec3",
          "value": {
            "x": 0,
            "y": 0,
            "z": 0
          },
          "internalOptional": true,
          "anchor": {
            "size": 16,
            "x": 0,
            "y": 43.75,
            "type": "field",
            "hovered": false,
            "active": false
          }
        },
        "frequency": {
          "kind": "dynamic",
          "type": "float",
          "value": 5.6,
          "min": 0,
          "max": 10,
          "anchor": {
            "size": 16,
            "x": 0,
            "y": 72.75,
            "type": "field",
            "hovered": false,
            "active": false
          },
          "previousStaticValue": 8.1
        },
        "amplitude": {
          "kind": "dynamic",
          "type": "float",
          "value": 4.6,
          "min": 0,
          "max": 10,
          "anchor": {
            "size": 16,
            "x": 0,
            "y": 101.75,
            "type": "field",
            "hovered": false,
            "active": false
          }
        },
        "persistance": {
          "kind": "dynamic",
          "type": "float",
          "value": 0.17,
          "min": 0,
          "max": 1,
          "anchor": {
            "size": 16,
            "x": 0,
            "y": 130.75,
            "type": "field",
            "hovered": false,
            "active": false
          },
          "previousStaticValue": 0.5
        },
        "lacunarity": {
          "kind": "dynamic",
          "type": "float",
          "value": 0,
          "min": 0,
          "max": 10,
          "anchor": {
            "size": 16,
            "x": 0,
            "y": 159.75,
            "type": "field",
            "hovered": false,
            "active": false
          },
          "previousStaticValue": 0.4
        },
        "octaves": {
          "kind": "static",
          "type": "int",
          "value": 4,
          "min": 1,
          "max": 5,
          "restricted": true,
          "anchor": {
            "size": 16,
            "x": 0,
            "y": 188.75,
            "type": "field",
            "active": false,
            "hovered": false
          }
        },
        "exponent": {
          "kind": "dynamic",
          "type": "float",
          "value": {
            "nodeId": "17"
          },
          "min": 0.01,
          "max": 10,
          "anchor": {
            "size": 16,
            "x": 0,
            "y": 217.75,
            "type": "field",
            "hovered": false,
            "active": false
          },
          "previousStaticValue": 2.008
        },
        "ridge": {
          "kind": "dynamic",
          "type": "float",
          "value": 0.73027,
          "min": 0.001,
          "max": 1,
          "restricted": true,
          "anchor": {
            "size": 16,
            "x": 0,
            "y": 246.75,
            "type": "field",
            "hovered": false,
            "active": false
          },
          "previousStaticValue": 0.74026
        },
        "normalize": {
          "kind": "static",
          "type": "bool",
          "value": true,
          "anchor": {
            "size": 16,
            "x": 0,
            "y": 275.75,
            "type": "field",
            "active": false,
            "hovered": false
          }
        }
      },
      "returnType": "float",
      "id": "19",
      "elevated": false,
      "active": false,
      "hovered": false
    },
    "20": {
      "type": "remap",
      "x": -415.44135188866846,
      "y": 195.55377733598382,
      "width": 200,
      "height": 134,
      "anchor": {
        "size": 16,
        "x": 200,
        "y": 67,
        "type": "node",
        "hovered": false,
        "active": false
      },
      "layer": 24,
      "fields": {
        "value": {
          "kind": "dynamic",
          "type": "float",
          "value": {
            "nodeId": "19"
          },
          "anchor": {
            "size": 16,
            "x": 0,
            "y": 48.25,
            "type": "field",
            "hovered": false,
            "active": false
          },
          "previousStaticValue": 0
        },
        "add": {
          "kind": "dynamic",
          "type": "float",
          "value": -1.2,
          "min": -10,
          "max": 10,
          "anchor": {
            "size": 16,
            "x": 0,
            "y": 81.75,
            "type": "field",
            "active": false,
            "hovered": false
          }
        },
        "mult": {
          "kind": "dynamic",
          "type": "float",
          "value": 700,
          "min": -10,
          "max": 10,
          "anchor": {
            "size": 16,
            "x": 0,
            "y": 115.25,
            "type": "field",
            "active": false,
            "hovered": false
          }
        }
      },
      "returnType": "float",
      "id": "20",
      "elevated": false,
      "active": false,
      "hovered": false
    },
    "23": {
      "type": "circle",
      "x": -17.938364456356183,
      "y": 445.91978047134614,
      "width": 200,
      "height": 238,
      "anchor": {
        "size": 16,
        "x": 200,
        "y": 119,
        "type": "node",
        "hovered": false,
        "active": false
      },
      "layer": 29,
      "fields": {
        "point": {
          "kind": "dynamic",
          "type": "vec3",
          "value": {
            "nodeId": "16"
          },
          "internalOptional": true,
          "anchor": {
            "size": 16,
            "x": 0,
            "y": 44.5,
            "type": "field",
            "hovered": false,
            "active": false
          },
          "previousStaticValue": {
            "x": 0,
            "y": 0,
            "z": 0
          }
        },
        "scale": {
          "kind": "static",
          "type": "float",
          "internal": true,
          "anchor": {
            "size": 16,
            "x": 0,
            "y": -4,
            "type": "field",
            "active": false,
            "hovered": false
          }
        },
        "radius": {
          "kind": "dynamic",
          "type": "float",
          "value": {
            "nodeId": "25"
          },
          "min": 0,
          "max": 1000,
          "anchor": {
            "size": 16,
            "x": 0,
            "y": 74.25,
            "type": "field",
            "hovered": false,
            "active": false
          },
          "previousStaticValue": 520
        },
        "x": {
          "kind": "dynamic",
          "type": "float",
          "value": 0,
          "min": -1000,
          "max": 1000,
          "anchor": {
            "size": 16,
            "x": 0,
            "y": 104,
            "type": "field",
            "hovered": false,
            "active": false
          },
          "previousStaticValue": 0
        },
        "y": {
          "kind": "dynamic",
          "type": "float",
          "value": 0,
          "min": -1000,
          "max": 1000,
          "anchor": {
            "size": 16,
            "x": 0,
            "y": 133.75,
            "type": "field",
            "hovered": false,
            "active": false
          }
        },
        "outsideBrightness": {
          "kind": "dynamic",
          "type": "float",
          "value": 0.04,
          "min": 0,
          "max": 1,
          "anchor": {
            "size": 16,
            "x": 0,
            "y": 163.5,
            "type": "field",
            "hovered": false,
            "active": false
          }
        },
        "insideBrightness": {
          "kind": "dynamic",
          "type": "float",
          "value": 0.85,
          "min": 0,
          "max": 1,
          "anchor": {
            "size": 16,
            "x": 0,
            "y": 193.25,
            "type": "field",
            "active": false,
            "hovered": false
          }
        },
        "softness": {
          "kind": "dynamic",
          "type": "float",
          "value": 1,
          "min": 0,
          "max": 1,
          "anchor": {
            "size": 16,
            "x": 0,
            "y": 223,
            "type": "field",
            "hovered": false,
            "active": false
          },
          "previousStaticValue": 1
        }
      },
      "returnType": "float",
      "id": "23",
      "elevated": false,
      "active": false,
      "hovered": false
    },
    "24": {
      "type": "combine",
      "x": 420.39324233164496,
      "y": 200.9227601497739,
      "width": 200,
      "height": 134,
      "anchor": {
        "size": 16,
        "x": 200,
        "y": 67,
        "type": "node",
        "hovered": false,
        "active": false
      },
      "layer": 21,
      "fields": {
        "operation": {
          "kind": "choice",
          "type": "int",
          "value": 0,
          "choices": {
            "add": 0,
            "mult": 1,
            "pow": 2,
            "avg": 3,
            "mod": 4
          },
          "anchor": {
            "size": 16,
            "x": 0,
            "y": 48.25,
            "type": "field",
            "active": false,
            "hovered": false
          }
        },
        "value1": {
          "kind": "dynamic",
          "type": "float",
          "value": {
            "nodeId": "15"
          },
          "anchor": {
            "size": 16,
            "x": 0,
            "y": 81.75,
            "type": "field",
            "hovered": false,
            "active": false
          },
          "previousStaticValue": 0
        },
        "value2": {
          "kind": "dynamic",
          "type": "float",
          "value": {
            "nodeId": "23"
          },
          "anchor": {
            "size": 16,
            "x": 0,
            "y": 115.25,
            "type": "field",
            "hovered": false,
            "active": false
          },
          "previousStaticValue": 0
        }
      },
      "returnType": "float",
      "id": "24",
      "elevated": false,
      "active": false,
      "hovered": false
    },
    "25": {
      "type": "remap",
      "x": -416.63479125248534,
      "y": 440.20884691849096,
      "width": 200,
      "height": 134,
      "anchor": {
        "size": 16,
        "x": 200,
        "y": 67,
        "type": "node",
        "hovered": false,
        "active": false
      },
      "layer": 18,
      "fields": {
        "value": {
          "kind": "dynamic",
          "type": "float",
          "value": {
            "nodeId": "19"
          },
          "anchor": {
            "size": 16,
            "x": 0,
            "y": 48.25,
            "type": "field",
            "hovered": false,
            "active": false
          },
          "previousStaticValue": 0
        },
        "add": {
          "kind": "dynamic",
          "type": "float",
          "value": 0,
          "min": -10,
          "max": 10,
          "anchor": {
            "size": 16,
            "x": 0,
            "y": 81.75,
            "type": "field",
            "active": false,
            "hovered": false
          }
        },
        "mult": {
          "kind": "dynamic",
          "type": "float",
          "value": 170,
          "min": -10,
          "max": 10,
          "anchor": {
            "size": 16,
            "x": 0,
            "y": 115.25,
            "type": "field",
            "active": false,
            "hovered": false
          }
        }
      },
      "returnType": "float",
      "id": "25",
      "elevated": false,
      "active": false,
      "hovered": false
    },
    "28": {
      "type": "simplex",
      "x": -693.7918815226419,
      "y": -270.077210972535,
      "width": 200,
      "height": 290,
      "anchor": {
        "size": 16,
        "x": 200,
        "y": 145,
        "type": "node",
        "hovered": false,
        "active": false
      },
      "layer": 22,
      "fields": {
        "point": {
          "kind": "dynamic",
          "type": "vec3",
          "value": {
            "x": 0,
            "y": 0,
            "z": 0
          },
          "internalOptional": true,
          "anchor": {
            "size": 16,
            "x": 0,
            "y": 43.75,
            "type": "field",
            "active": false,
            "hovered": false
          }
        },
        "frequency": {
          "kind": "dynamic",
          "type": "float",
          "value": 0.4,
          "min": 0,
          "max": 10,
          "anchor": {
            "size": 16,
            "x": 0,
            "y": 72.75,
            "type": "field",
            "active": false,
            "hovered": false
          }
        },
        "amplitude": {
          "kind": "dynamic",
          "type": "float",
          "value": 4.8,
          "min": 0,
          "max": 10,
          "anchor": {
            "size": 16,
            "x": 0,
            "y": 101.75,
            "type": "field",
            "active": false,
            "hovered": false
          }
        },
        "persistance": {
          "kind": "dynamic",
          "type": "float",
          "value": 0.6,
          "min": 0,
          "max": 1,
          "anchor": {
            "size": 16,
            "x": 0,
            "y": 130.75,
            "type": "field",
            "active": false,
            "hovered": false
          }
        },
        "lacunarity": {
          "kind": "dynamic",
          "type": "float",
          "value": 2.8,
          "min": 0,
          "max": 10,
          "anchor": {
            "size": 16,
            "x": 0,
            "y": 159.75,
            "type": "field",
            "active": false,
            "hovered": false
          }
        },
        "octaves": {
          "kind": "static",
          "type": "int",
          "value": 4,
          "min": 1,
          "max": 5,
          "restricted": true,
          "anchor": {
            "size": 16,
            "x": 0,
            "y": 188.75,
            "type": "field",
            "active": false,
            "hovered": false
          }
        },
        "exponent": {
          "kind": "dynamic",
          "type": "float",
          "value": 2.3077,
          "min": 0.01,
          "max": 10,
          "anchor": {
            "size": 16,
            "x": 0,
            "y": 217.75,
            "type": "field",
            "hovered": false,
            "active": false
          }
        },
        "ridge": {
          "kind": "dynamic",
          "type": "float",
          "value": 0.25075,
          "min": 0.001,
          "max": 1,
          "restricted": true,
          "anchor": {
            "size": 16,
            "x": 0,
            "y": 246.75,
            "type": "field",
            "active": false,
            "hovered": false
          }
        },
        "normalize": {
          "kind": "static",
          "type": "bool",
          "value": true,
          "anchor": {
            "size": 16,
            "x": 0,
            "y": 275.75,
            "type": "field",
            "active": false,
            "hovered": false
          }
        }
      },
      "returnType": "float",
      "id": "28",
      "elevated": false,
      "active": false,
      "hovered": true
    },
    "29": {
      "type": "remap",
      "x": 388.01177603975077,
      "y": -124.30464140893315,
      "width": 200,
      "height": 134,
      "anchor": {
        "size": 16,
        "x": 200,
        "y": 67,
        "type": "node",
        "hovered": false,
        "active": false
      },
      "layer": 23,
      "fields": {
        "value": {
          "kind": "dynamic",
          "type": "float",
          "value": {
            "nodeId": "23"
          },
          "anchor": {
            "size": 16,
            "x": 0,
            "y": 48.25,
            "type": "field",
            "hovered": false,
            "active": false
          },
          "previousStaticValue": 0
        },
        "add": {
          "kind": "dynamic",
          "type": "float",
          "value": -2.8,
          "min": -10,
          "max": 10,
          "anchor": {
            "size": 16,
            "x": 0,
            "y": 81.75,
            "type": "field",
            "hovered": false,
            "active": false
          },
          "previousStaticValue": 5.4
        },
        "mult": {
          "kind": "dynamic",
          "type": "float",
          "value": {
            "nodeId": "17"
          },
          "min": -10,
          "max": 10,
          "anchor": {
            "size": 16,
            "x": 0,
            "y": 115.25,
            "type": "field",
            "hovered": false,
            "active": false
          },
          "previousStaticValue": 0.2
        }
      },
      "returnType": "float",
      "id": "29",
      "elevated": false,
      "active": false,
      "hovered": false
    },
    "31": {
      "type": "combine",
      "x": 485.19508333849967,
      "y": 398.69499918565225,
      "width": 200,
      "height": 134,
      "anchor": {
        "size": 16,
        "x": 200,
        "y": 67,
        "type": "node",
        "hovered": false,
        "active": false
      },
      "layer": 26,
      "fields": {
        "operation": {
          "kind": "choice",
          "type": "int",
          "value": 2,
          "choices": {
            "add": 0,
            "mult": 1,
            "pow": 2,
            "avg": 3,
            "mod": 4
          },
          "anchor": {
            "size": 16,
            "x": 0,
            "y": 48.25,
            "type": "field",
            "active": false,
            "hovered": false
          }
        },
        "value1": {
          "kind": "dynamic",
          "type": "float",
          "value": {
            "nodeId": "15"
          },
          "anchor": {
            "size": 16,
            "x": 0,
            "y": 81.75,
            "type": "field",
            "hovered": false,
            "active": false
          },
          "previousStaticValue": 0
        },
        "value2": {
          "kind": "dynamic",
          "type": "float",
          "value": {
            "nodeId": "23"
          },
          "anchor": {
            "size": 16,
            "x": 0,
            "y": 115.25,
            "type": "field",
            "hovered": false,
            "active": false
          },
          "previousStaticValue": 0
        }
      },
      "returnType": "float",
      "id": "31",
      "elevated": false,
      "active": false,
      "hovered": false
    }
  },
  "position": {
    "x": -420.2392064761483,
    "y": -218.2611838921258
  },
  "zoom": 1.27872772761512
}